[
  {
    "ProductId": 1005004887424278,
    "Image Url": "https://ae04.alicdn.com/kf/S91bb4df61c1645dbb656182d15b415a7v.jpg",
    "Video Url": "http://cloud.video.taobao.com/play/u/2675628091/p/1/e/6/t/1/1100095636020.mp4",
    "Product Desc": "Electric scooter 1200W super motor, top speed 30mph range 40 miles 10.5\" off-road tyres  52V 18AH disc brake suitable for adults",
    "Origin Price": "USD 1055.00",
    "Discount Price": "USD 949.50",
    "Discount": "10%",
    "Currency": "USD",
    "Commission Rate": 7,
    "Commission": "USD 66.46",
    "Sales180Day": 2,
    "Positive Feedback": "100.0%",
    "Promotion Url": "https://s.click.aliexpress.com/e/_Dk0UOyT",
    "Code Name": "",
    "Code Start Time": "",
    "Code End Time": "",
    "Code Value": "",
    "Code Quantity": "",
    "Code Minimum Spend": ""
  },
  {
    "ProductId": 1005005104632123,
    "Image Url": "https://ae04.alicdn.com/kf/S01a646d2272540938bc7111e679acfcbC.jpg",
    "Video Url": "http://cloud.video.taobao.com/play/u/2675628091/p/1/e/6/t/1/1100083993255.mp4",
    "Product Desc": "2600W Outdoor Waterproof Foldable Electric Scooter with 10 inch Vacuum Tires Front Rear BLDC Gear Motors 75km/h Fast Speed",
    "Origin Price": "USD 1141.42",
    "Discount Price": "USD 798.99",
    "Discount": "30%",
    "Currency": "USD",
    "Commission Rate": 8,
    "Commission": "USD 63.92",
    "Sales180Day": 0,
    "Positive Feedback": "null%",
    "Promotion Url": "https://s.click.aliexpress.com/e/_Dma8zWL",
    "Code Name": "",
    "Code Start Time": "",
    "Code End Time": "",
    "Code Value": "",
    "Code Quantity": "",
    "Code Minimum Spend": ""
  },
  {
    "ProductId": 1005004255717546,
    "Image Url": "https://ae04.alicdn.com/kf/S5821ba1426b74122a5cd6f3df84b0fb9h.jpg",
    "Video Url": "http://cloud.video.taobao.com/play/u/2675628091/p/1/e/6/t/1/1100024354558.mp4",
    "Product Desc": "6000W High Power Electric Scooter 100km/h High Speed 13 inch Off Road Tire E scooter Foldable 60V 30AH Battery электросамокат",
    "Origin Price": "USD 1038.94",
    "Discount Price": "USD 685.70",
    "Discount": "34%",
    "Currency": "USD",
    "Commission Rate": 8,
    "Commission": "USD 54.86",
    "Sales180Day": 8,
    "Positive Feedback": "100.0%",
    "Promotion Url": "https://s.click.aliexpress.com/e/_DdYEDa3",
    "Code Name": "",
    "Code Start Time": "",
    "Code End Time": "",
    "Code Value": "",
    "Code Quantity": "",
    "Code Minimum Spend": ""
  },
  {
    "ProductId": 1005004934235640,
    "Image Url": "https://ae04.alicdn.com/kf/S332b855e19e645a5ab21bdebfc76e48cO.jpg",
    "Video Url": "http://cloud.video.taobao.com/play/u/2675628091/p/1/e/6/t/1/1100100591449.mp4",
    "Product Desc": "10 inch 48V 550W adult folding electric scooter aviation pure aluminum alloy integrated molding battery car 40km/h",
    "Origin Price": "USD 1541.88",
    "Discount Price": "USD 735.60",
    "Discount": "0%",
    "Currency": "USD",
    "Commission Rate": 7,
    "Commission": "USD 51.49",
    "Sales180Day": 6,
    "Positive Feedback": "100.0%",
    "Promotion Url": "https://s.click.aliexpress.com/e/_DEEkfHh",
    "Code Name": "",
    "Code Start Time": "",
    "Code End Time": "",
    "Code Value": "",
    "Code Quantity": "",
    "Code Minimum Spend": ""
  },
  {
    "ProductId": 1005005123644838,
    "Image Url": "https://ae04.alicdn.com/kf/Scc0198c21acf4516ac32c45609215ba8J.jpg",
    "Video Url": "",
    "Product Desc": "500W 800W 60V 48V20A 35A Electric Tricycle Pulling goods Household Small Old Scooter Covered Battery car  Pick Up the Child",
    "Origin Price": "USD 3051.85",
    "Discount Price": "USD 305.18",
    "Discount": "90%",
    "Currency": "USD",
    "Commission Rate": 7,
    "Commission": "USD 21.36",
    "Sales180Day": 0,
    "Positive Feedback": "null%",
    "Promotion Url": "https://s.click.aliexpress.com/e/_DePf2tH",
    "Code Name": "",
    "Code Start Time": "",
    "Code End Time": "",
    "Code Value": "",
    "Code Quantity": "",
    "Code Minimum Spend": ""
  },
  {
    "ProductId": 1005004690909101,
    "Image Url": "https://ae04.alicdn.com/kf/Sfad0b038ac4247e2ab929beb34d49fbdb.jpg",
    "Video Url": "http://cloud.video.taobao.com/play/u/2675628091/p/1/e/6/t/1/1100084344150.mp4",
    "Product Desc": "Sealup Hot Seller Stock High Speed Two Wheel Off Road Electric Electrique Patin Adult Electric Scooter",
    "Origin Price": "USD 1423.61",
    "Discount Price": "USD 854.17",
    "Discount": "40%",
    "Currency": "USD",
    "Commission Rate": 7,
    "Commission": "USD 59.79",
    "Sales180Day": 3,
    "Positive Feedback": "100.0%",
    "Promotion Url": "https://s.click.aliexpress.com/e/_DFe1XLV",
    "Code Name": "",
    "Code Start Time": "",
    "Code End Time": "",
    "Code Value": "",
    "Code Quantity": "",
    "Code Minimum Spend": ""
  },
  {
    "ProductId": 1005004946902414,
    "Image Url": "https://ae04.alicdn.com/kf/Sd41609eb6ef642079badb3eca77d6aa9t.jpg",
    "Video Url": "",
    "Product Desc": "HEZZO UK Warehouse Free Shipping 48V 500W 10AH Lithium Battery 10 Inch Foldable Fat Electric Kick Scooters For Adult",
    "Origin Price": "USD 1649.00",
    "Discount Price": "USD 1649.00",
    "Discount": "0%",
    "Currency": "USD",
    "Commission Rate": 7,
    "Commission": "USD 115.43",
    "Sales180Day": 0,
    "Positive Feedback": "null%",
    "Promotion Url": "https://s.click.aliexpress.com/e/_DDggzMX",
    "Code Name": "",
    "Code Start Time": "",
    "Code End Time": "",
    "Code Value": "",
    "Code Quantity": "",
    "Code Minimum Spend": ""
  },
  {
    "ProductId": 1005004667032619,
    "Image Url": "https://ae04.alicdn.com/kf/Sdf3f5bd773ba477da3faebfc8aeac6a8p.jpg",
    "Video Url": "",
    "Product Desc": "SEALUP Q9 HOT SALE 8 INCH 2 WHEELS FOLDABLE ELECTRIC SCOOTER WITH GOOD PRICE FRAME AND ACCESSORIES FOR SALE",
    "Origin Price": "USD 757.30",
    "Discount Price": "USD 454.38",
    "Discount": "40%",
    "Currency": "USD",
    "Commission Rate": 7,
    "Commission": "USD 31.81",
    "Sales180Day": 1,
    "Positive Feedback": "null%",
    "Promotion Url": "https://s.click.aliexpress.com/e/_DkEYRgB",
    "Code Name": "",
    "Code Start Time": "",
    "Code End Time": "",
    "Code Value": "",
    "Code Quantity": "",
    "Code Minimum Spend": ""
  },
  {
    "ProductId": 1005002748110821,
    "Image Url": "https://ae04.alicdn.com/kf/H21ef6a1d68d24c5cbb32c48089614843q.jpg",
    "Video Url": "http://cloud.video.taobao.com/play/u/2675628091/p/1/e/6/t/1/312508761321.mp4",
    "Product Desc": "No Taxes RU Stock M365 Electric Scooter Foldable 25KM/H 350W 30KM Range 8.5 Inch 7.8Ah Safe Battery Kick Scooter For Adults Kids",
    "Origin Price": "USD 426.99",
    "Discount Price": "USD 426.99",
    "Discount": "0%",
    "Currency": "USD",
    "Commission Rate": 8,
    "Commission": "USD 34.16",
    "Sales180Day": 0,
    "Positive Feedback": "null%",
    "Promotion Url": "https://s.click.aliexpress.com/e/_DFHrknv",
    "Code Name": "",
    "Code Start Time": "",
    "Code End Time": "",
    "Code Value": "",
    "Code Quantity": "",
    "Code Minimum Spend": ""
  },
  {
    "ProductId": 1005004748896627,
    "Image Url": "https://ae04.alicdn.com/kf/S27eb89c92bfc421fb2474c21cf324de6G.jpg",
    "Video Url": "http://cloud.video.taobao.com/play/u/2675628091/p/1/e/6/t/1/1100112492801.mp4",
    "Product Desc": "Electric Scooters 8.5 Inch APP Control Smart Skateboard 350W Motor 25 KM/H Speed Shock Absorption Folded Adult Kick E-Scooter",
    "Origin Price": "USD 699.00",
    "Discount Price": "USD 356.49",
    "Discount": "49%",
    "Currency": "USD",
    "Commission Rate": 7,
    "Commission": "USD 24.95",
    "Sales180Day": 0,
    "Positive Feedback": "null%",
    "Promotion Url": "https://s.click.aliexpress.com/e/_DnCsJ27",
    "Code Name": "",
    "Code Start Time": "",
    "Code End Time": "",
    "Code Value": "",
    "Code Quantity": "",
    "Code Minimum Spend": ""
  },
  {
    "ProductId": 1005005123631179,
    "Image Url": "https://ae04.alicdn.com/kf/Sb32102688ca1461799d6897a134d4851Z.jpg",
    "Video Url": "",
    "Product Desc": "12 Inch Electric Adult Tricycle 3 Wheels Electro-tricycle 500W 48V 30AH, Range 110-120KM, Electric Scooter Seats/Basket",
    "Origin Price": "USD 3051.85",
    "Discount Price": "USD 305.18",
    "Discount": "90%",
    "Currency": "USD",
    "Commission Rate": 7,
    "Commission": "USD 21.36",
    "Sales180Day": 0,
    "Positive Feedback": "null%",
    "Promotion Url": "https://s.click.aliexpress.com/e/_DDc0IF1",
    "Code Name": "",
    "Code Start Time": "",
    "Code End Time": "",
    "Code Value": "",
    "Code Quantity": "",
    "Code Minimum Spend": ""
  },
  {
    "ProductId": 1005005044120420,
    "Image Url": "https://ae04.alicdn.com/kf/Sf511b2a47bd546d2b583935f504b62954.jpg",
    "Video Url": "http://cloud.video.taobao.com/play/u/2675628091/p/1/e/6/t/1/1100106958868.mp4",
    "Product Desc": "Free VAT Tax EU Stock OBARTER D5 48V 35Ah Dual Motor 5000W Rated Power Top Speed 70km/h Powerful Adult 12inch Electric Scooter",
    "Origin Price": "USD 1987.00",
    "Discount Price": "USD 1867.78",
    "Discount": "6%",
    "Currency": "USD",
    "Commission Rate": 7,
    "Commission": "USD 130.74",
    "Sales180Day": 3,
    "Positive Feedback": "100.0%",
    "Promotion Url": "https://s.click.aliexpress.com/e/_DFnIZSb",
    "Code Name": "",
    "Code Start Time": "",
    "Code End Time": "",
    "Code Value": "",
    "Code Quantity": "",
    "Code Minimum Spend": ""
  },
  {
    "ProductId": 1005004314628617,
    "Image Url": "https://ae04.alicdn.com/kf/S1934777f4d634bc7af448674c09c57ecg.png",
    "Video Url": "",
    "Product Desc": "Electric Scooter Speed Dial Thumb Accelerator For Xiaomi M365 Scooter Accessories Trigger Shifter Dial Scooters Thumb Throttle",
    "Origin Price": "USD 6.61",
    "Discount Price": "USD 4.83",
    "Discount": "27%",
    "Currency": "USD",
    "Commission Rate": 7,
    "Commission": "USD 0.34",
    "Sales180Day": 1,
    "Positive Feedback": "null%",
    "Promotion Url": "https://s.click.aliexpress.com/e/_De8p1qj",
    "Code Name": "",
    "Code Start Time": "",
    "Code End Time": "",
    "Code Value": "",
    "Code Quantity": "",
    "Code Minimum Spend": ""
  },
  {
    "ProductId": 1005004996065404,
    "Image Url": "https://ae04.alicdn.com/kf/Sfaa7593bc5f3412f91bfd520b27fac04t.jpg",
    "Video Url": "http://cloud.video.taobao.com/play/u/2675628091/p/1/e/6/t/1/1100104033235.mp4",
    "Product Desc": "Off-road Electric Scooter 45km/h Adult Scooter Z00M Mechanical Brake 10INCH 1000W Adult Foldable Electric Skateboards Scooter",
    "Origin Price": "USD 1798.00",
    "Discount Price": "USD 899.00",
    "Discount": "50%",
    "Currency": "USD",
    "Commission Rate": 10,
    "Commission": "USD 89.90",
    "Sales180Day": 0,
    "Positive Feedback": "null%",
    "Promotion Url": "https://s.click.aliexpress.com/e/_DczWhfz",
    "Code Name": "",
    "Code Start Time": "",
    "Code End Time": "",
    "Code Value": "",
    "Code Quantity": "",
    "Code Minimum Spend": ""
  },
  {
    "ProductId": 1005005134068902,
    "Image Url": "https://ae04.alicdn.com/kf/S75095c1c1965464ba10c0fdcabc7bc0co.jpg",
    "Video Url": "",
    "Product Desc": "Original Kaabo LT01 Display Thumb Throttle for Kaabo Mantis 8/10 Kaabo Wolf Warrior X Kaabo Wolf Warrior 11 Electric Scooter",
    "Origin Price": "USD 46.39",
    "Discount Price": "USD 32.47",
    "Discount": "30%",
    "Currency": "USD",
    "Commission Rate": 7,
    "Commission": "USD 2.27",
    "Sales180Day": 0,
    "Positive Feedback": "null%",
    "Promotion Url": "https://s.click.aliexpress.com/e/_DDz3mtV",
    "Code Name": "",
    "Code Start Time": "",
    "Code End Time": "",
    "Code Value": "",
    "Code Quantity": "",
    "Code Minimum Spend": ""
  },
  {
    "ProductId": 1005004546392826,
    "Image Url": "https://ae04.alicdn.com/kf/S6628b00d219d4b288c0f6eb9c337be9fy.jpg",
    "Video Url": "http://cloud.video.taobao.com/play/u/2675628091/p/1/e/6/t/1/333317842279.mp4",
    "Product Desc": "High-end adult electric scooter 30km/h 8.5-inch 350W ultra-light folding scooter Lithium battery with APP and Bluetooth",
    "Origin Price": "USD 538.00",
    "Discount Price": "USD 269.00",
    "Discount": "50%",
    "Currency": "USD",
    "Commission Rate": 7,
    "Commission": "USD 18.83",
    "Sales180Day": 4,
    "Positive Feedback": "null%",
    "Promotion Url": "https://s.click.aliexpress.com/e/_Dlo4vMr",
    "Code Name": "",
    "Code Start Time": "",
    "Code End Time": "",
    "Code Value": "",
    "Code Quantity": "",
    "Code Minimum Spend": ""
  },
  {
    "ProductId": 1005005048616547,
    "Image Url": "https://ae04.alicdn.com/kf/S35ac34b8d9434ed2980a4acf709da7259.jpg",
    "Video Url": "",
    "Product Desc": "Free VAT Tax Original Kaabo 84V 1.5A Charger Spare Part Suit for 72V Kaabo Wolf King GT Electric Scooter Official Kaabo King GT",
    "Origin Price": "USD 33.14",
    "Discount Price": "USD 33.14",
    "Discount": "0%",
    "Currency": "USD",
    "Commission Rate": 7,
    "Commission": "USD 2.32",
    "Sales180Day": 0,
    "Positive Feedback": "null%",
    "Promotion Url": "https://s.click.aliexpress.com/e/_DkmeRkf",
    "Code Name": "",
    "Code Start Time": "",
    "Code End Time": "",
    "Code Value": "",
    "Code Quantity": "",
    "Code Minimum Spend": ""
  },
  {
    "ProductId": 1005004725347887,
    "Image Url": "https://ae04.alicdn.com/kf/S082bdd925b3942489011c4fb6b601eddx.jpg",
    "Video Url": "http://cloud.video.taobao.com/play/u/2675628091/p/1/e/6/t/1/1100086395614.mp4",
    "Product Desc": "AOVOPRO M365 Electric Scooter 350W 7.8Ah 25km/h Smart APP E Scooter Foldable Adult Electric Scooter Waterproof Grade IP65",
    "Origin Price": "USD 557.96",
    "Discount Price": "USD 278.98",
    "Discount": "50%",
    "Currency": "USD",
    "Commission Rate": 8,
    "Commission": "USD 22.32",
    "Sales180Day": 1,
    "Positive Feedback": "null%",
    "Promotion Url": "https://s.click.aliexpress.com/e/_DnPC8n1",
    "Code Name": "",
    "Code Start Time": "",
    "Code End Time": "",
    "Code Value": "",
    "Code Quantity": "",
    "Code Minimum Spend": ""
  },
  {
    "ProductId": 1005004891155954,
    "Image Url": "https://ae04.alicdn.com/kf/S47032ed999474b82a7b0a97e700db50cZ.jpg",
    "Video Url": "",
    "Product Desc": "T08 3200W Dual Motor Adults Electric Scooter 10\" ‎Solid Off-Road Tire 60V 21A Battery 70KM/H Foldable Scooter",
    "Origin Price": "USD 1726.00",
    "Discount Price": "USD 1553.40",
    "Discount": "10%",
    "Currency": "USD",
    "Commission Rate": 7,
    "Commission": "USD 108.74",
    "Sales180Day": 0,
    "Positive Feedback": "null%",
    "Promotion Url": "https://s.click.aliexpress.com/e/_DdKds9V",
    "Code Name": "",
    "Code Start Time": "",
    "Code End Time": "",
    "Code Value": "",
    "Code Quantity": "",
    "Code Minimum Spend": ""
  },
  {
    "ProductId": 32768947482,
    "Image Url": "https://ae04.alicdn.com/kf/Sb6484e253e684f80b348c41bb2d6a1477.jpg",
    "Video Url": "",
    "Product Desc": "RUIMA  leger pro  Electric Scooter 52V 600w motor  8.5Inch Tire  LEGER PRO  Electric Motorcycle Skateboard PowerScooter",
    "Origin Price": "USD 779.00",
    "Discount Price": "USD 740.05",
    "Discount": "5%",
    "Currency": "USD",
    "Commission Rate": 7,
    "Commission": "USD 51.80",
    "Sales180Day": 10,
    "Positive Feedback": "80.0%",
    "Promotion Url": "https://s.click.aliexpress.com/e/_DncCSBZ",
    "Code Name": "",
    "Code Start Time": "",
    "Code End Time": "",
    "Code Value": "",
    "Code Quantity": "",
    "Code Minimum Spend": ""
  },
  {
    "ProductId": 1005004960890812,
    "Image Url": "https://ae04.alicdn.com/kf/S10d0543ac0954749b51bb9a625eecb618.jpg",
    "Video Url": "http://cloud.video.taobao.com/play/u/2675628091/p/1/e/6/t/1/1100098722727.mp4",
    "Product Desc": "350w Electric Scooter 10 inch Tire 36v 10ah Removable battery Foldable Electric Scooters For Adult 33km/h Speed New Design Gift",
    "Origin Price": "USD 799.00",
    "Discount Price": "USD 407.49",
    "Discount": "49%",
    "Currency": "USD",
    "Commission Rate": 7,
    "Commission": "USD 28.52",
    "Sales180Day": 1,
    "Positive Feedback": "null%",
    "Promotion Url": "https://s.click.aliexpress.com/e/_DdWVX6T",
    "Code Name": "",
    "Code Start Time": "",
    "Code End Time": "",
    "Code Value": "",
    "Code Quantity": "",
    "Code Minimum Spend": ""
  },
  {
    "ProductId": 32967355667,
    "Image Url": "https://ae04.alicdn.com/kf/S59c104fb16f2418c8437cf52e07afda1I.jpg",
    "Video Url": "http://cloud.video.taobao.com/play/u/2675628091/p/1/e/6/t/1/264193156190.mp4",
    "Product Desc": "Upgarde RUIMA mini4 PRO waterproof version with bell  48V 500W BLDC HUB strong power electric scooter powerful scooter",
    "Origin Price": "USD 606.00",
    "Discount Price": "USD 551.46",
    "Discount": "9%",
    "Currency": "USD",
    "Commission Rate": 7,
    "Commission": "USD 38.60",
    "Sales180Day": 16,
    "Positive Feedback": "100.0%",
    "Promotion Url": "https://s.click.aliexpress.com/e/_Dm7w25d",
    "Code Name": "",
    "Code Start Time": "",
    "Code End Time": "",
    "Code Value": "",
    "Code Quantity": "",
    "Code Minimum Spend": ""
  },
  {
    "ProductId": 1005004674243924,
    "Image Url": "https://ae04.alicdn.com/kf/S585db598e2b14c7989e48af123a919a7i.jpg",
    "Video Url": "http://cloud.video.taobao.com/play/u/2675628091/p/1/e/6/t/1/1100093865707.mp4",
    "Product Desc": "SEALUP Q21 ADULT ELECTRIC SCOOTER MAXIMUM SPEED 50MPH 80-100KM LONG BATTERY LIFE 500W MOTOR 10INCH WHEELS PORTABLE FOLDING",
    "Origin Price": "USD 763.23",
    "Discount Price": "USD 457.94",
    "Discount": "40%",
    "Currency": "USD",
    "Commission Rate": 7,
    "Commission": "USD 32.06",
    "Sales180Day": 3,
    "Positive Feedback": "null%",
    "Promotion Url": "https://s.click.aliexpress.com/e/_DmrT4Or",
    "Code Name": "",
    "Code Start Time": "",
    "Code End Time": "",
    "Code Value": "",
    "Code Quantity": "",
    "Code Minimum Spend": ""
  },
  {
    "ProductId": 1005004691112414,
    "Image Url": "https://ae04.alicdn.com/kf/Se5915ac2632b4b6186c4fc446453e9f6R.jpg",
    "Video Url": "http://cloud.video.taobao.com/play/u/2675628091/p/1/e/6/t/1/1100084346798.mp4",
    "Product Desc": "SEALUP Electric Scooter 50KM/H Scooter Electric 10 inch Off Road E Scooter 48V 1000W Foldable Adult Electric Scooter",
    "Origin Price": "USD 1170.78",
    "Discount Price": "USD 702.47",
    "Discount": "40%",
    "Currency": "USD",
    "Commission Rate": 7,
    "Commission": "USD 49.17",
    "Sales180Day": 7,
    "Positive Feedback": "100.0%",
    "Promotion Url": "https://s.click.aliexpress.com/e/_DnNnmEX",
    "Code Name": "",
    "Code Start Time": "",
    "Code End Time": "",
    "Code Value": "",
    "Code Quantity": "",
    "Code Minimum Spend": ""
  },
  {
    "ProductId": 1005003218952634,
    "Image Url": "https://ae04.alicdn.com/kf/Hb8d7c95a0afa4a4b9032c2e5870f859f5.jpg",
    "Video Url": "",
    "Product Desc": "GT20 Pro Electric Bike 750W 48V10AH 45KM/H New Super Level Snow  4.0 Fat Tire E-Bicycle Beach E-Bike",
    "Origin Price": "USD 1130.00",
    "Discount Price": "USD 1130.00",
    "Discount": "0%",
    "Currency": "USD",
    "Commission Rate": 7,
    "Commission": "USD 79.10",
    "Sales180Day": 0,
    "Positive Feedback": "null%",
    "Promotion Url": "https://s.click.aliexpress.com/e/_DCWGAV5",
    "Code Name": "",
    "Code Start Time": "",
    "Code End Time": "",
    "Code Value": "",
    "Code Quantity": "",
    "Code Minimum Spend": ""
  },
  {
    "ProductId": 1005004693544937,
    "Image Url": "https://ae04.alicdn.com/kf/S34baa946ba8f4bcbb596dbe2f1c0ccafn.png",
    "Video Url": "http://cloud.video.taobao.com/play/u/2675628091/p/1/e/6/t/1/1100084491179.mp4",
    "Product Desc": "SEALUP ELECTRIC SCOOTER 3 GEARS HIGH SPEED WITH 10'' TIRES FOLDABLE SCOOTER ELECTRIC FOR ADULTS LOAD 400kg",
    "Origin Price": "USD 1198.94",
    "Discount Price": "USD 719.36",
    "Discount": "40%",
    "Currency": "USD",
    "Commission Rate": 7,
    "Commission": "USD 50.36",
    "Sales180Day": 6,
    "Positive Feedback": "100.0%",
    "Promotion Url": "https://s.click.aliexpress.com/e/_DkxbdwF",
    "Code Name": "",
    "Code Start Time": "",
    "Code End Time": "",
    "Code Value": "",
    "Code Quantity": "",
    "Code Minimum Spend": ""
  },
  {
    "ProductId": 1005004550088488,
    "Image Url": "https://ae04.alicdn.com/kf/S52fa32d62fad45be8ab4cd247969d957d.jpg",
    "Video Url": "",
    "Product Desc": "500W Self Balance Scooters 6.5'' Hoverboard Smart Electric Hover Board 2 Wheels LED Flash Lights Bluetooth Speaker Kids Gifts",
    "Origin Price": "USD 160.00",
    "Discount Price": "USD 152.00",
    "Discount": "5%",
    "Currency": "USD",
    "Commission Rate": 7,
    "Commission": "USD 10.64",
    "Sales180Day": 6,
    "Positive Feedback": "null%",
    "Promotion Url": "https://s.click.aliexpress.com/e/_DdhPFCf",
    "Code Name": "",
    "Code Start Time": "",
    "Code End Time": "",
    "Code Value": "",
    "Code Quantity": "",
    "Code Minimum Spend": ""
  },
  {
    "ProductId": 1005005021850942,
    "Image Url": "https://ae04.alicdn.com/kf/S00e3a2f0de2743ee857599bb2411506dV.png",
    "Video Url": "http://cloud.video.taobao.com/play/u/2675628091/p/1/e/6/t/1/1100105660462.mp4",
    "Product Desc": "Wholesale Price Retro Scooter  2022 New 72V Lithium Battery 3000W COC EEC Adult Royal  Electric Motorbike",
    "Origin Price": "USD 2199.00",
    "Discount Price": "USD 2199.00",
    "Discount": "0%",
    "Currency": "USD",
    "Commission Rate": 7,
    "Commission": "USD 153.93",
    "Sales180Day": 0,
    "Positive Feedback": "null%",
    "Promotion Url": "https://s.click.aliexpress.com/e/_DlDT4JD",
    "Code Name": "",
    "Code Start Time": "",
    "Code End Time": "",
    "Code Value": "",
    "Code Quantity": "",
    "Code Minimum Spend": ""
  },
  {
    "ProductId": 1005004537678728,
    "Image Url": "https://ae04.alicdn.com/kf/Sbb12e9cb80a647f19222004f9811e406Z.jpg",
    "Video Url": "http://cloud.video.taobao.com/play/u/2675628091/p/1/e/6/t/1/1100067260951.mp4",
    "Product Desc": "HEZZO EU US 60V 5600W Dual Motors Escooters 40Ah LG Battery 11Inch Fat Tire Foldable Off Road Electric Kick Scooters For Adult",
    "Origin Price": "USD 2199.00",
    "Discount Price": "USD 1649.25",
    "Discount": "25%",
    "Currency": "USD",
    "Commission Rate": 7,
    "Commission": "USD 115.45",
    "Sales180Day": 0,
    "Positive Feedback": "null%",
    "Promotion Url": "https://s.click.aliexpress.com/e/_DlWosYj",
    "Code Name": "",
    "Code Start Time": "",
    "Code End Time": "",
    "Code Value": "",
    "Code Quantity": "",
    "Code Minimum Spend": ""
  },
  {
    "ProductId": 1005005121046428,
    "Image Url": "https://ae04.alicdn.com/kf/S77c8a25a03fc4bcdaad839c120b3ddbdO.jpg",
    "Video Url": "http://cloud.video.taobao.com/play/u/2675628091/p/1/e/6/t/1/1100115487343.mp4",
    "Product Desc": "Free VAT Original Kaabo Mantis King GT Steering Damper Kit for Kaabo Mantis King GT Electric Scooter Official Kaabo Spare Part",
    "Origin Price": "USD 135.85",
    "Discount Price": "USD 95.10",
    "Discount": "30%",
    "Currency": "USD",
    "Commission Rate": 7,
    "Commission": "USD 6.66",
    "Sales180Day": 0,
    "Positive Feedback": "null%",
    "Promotion Url": "https://s.click.aliexpress.com/e/_DlLmMuT",
    "Code Name": "",
    "Code Start Time": "",
    "Code End Time": "",
    "Code Value": "",
    "Code Quantity": "",
    "Code Minimum Spend": ""
  },
  {
    "ProductId": 1005004678173094,
    "Image Url": "https://ae04.alicdn.com/kf/S9b0f978566e34b82b08c998b92894375e.jpg",
    "Video Url": "http://cloud.video.taobao.com/play/u/2675628091/p/1/e/6/t/1/1100083449072.mp4",
    "Product Desc": "70KM/H Max Speed Powerful Electric Scooter For Adult With Seat Dual Motor 2400W E Scooter 10\" Tire 40-70km/h Range",
    "Origin Price": "USD 2019.00",
    "Discount Price": "USD 1009.50",
    "Discount": "50%",
    "Currency": "USD",
    "Commission Rate": 7,
    "Commission": "USD 70.66",
    "Sales180Day": 0,
    "Positive Feedback": "null%",
    "Promotion Url": "https://s.click.aliexpress.com/e/_DBhxLbd",
    "Code Name": "",
    "Code Start Time": "",
    "Code End Time": "",
    "Code Value": "",
    "Code Quantity": "",
    "Code Minimum Spend": ""
  },
  {
    "ProductId": 1005005048998003,
    "Image Url": "https://ae04.alicdn.com/kf/S2727a3d3f45b47adaea0369bf523a1c41.jpg",
    "Video Url": "",
    "Product Desc": "500W Adults Electric Scooter Max Speed 35KM/H 36V 15AH 12'' Pneumatic Tire Smart Scooter Mens Lady Commuter Foldable E Scooter",
    "Origin Price": "USD 555.00",
    "Discount Price": "USD 471.75",
    "Discount": "15%",
    "Currency": "USD",
    "Commission Rate": 7,
    "Commission": "USD 33.02",
    "Sales180Day": 4,
    "Positive Feedback": "null%",
    "Promotion Url": "https://s.click.aliexpress.com/e/_DFczCdH",
    "Code Name": "",
    "Code Start Time": "",
    "Code End Time": "",
    "Code Value": "",
    "Code Quantity": "",
    "Code Minimum Spend": ""
  },
  {
    "ProductId": 1005004526857377,
    "Image Url": "https://ae04.alicdn.com/kf/Sb32532d4c0ce465d98d5412ac85e553bA.jpg",
    "Video Url": "http://cloud.video.taobao.com/play/u/2675628091/p/1/e/6/t/1/1100066034116.mp4",
    "Product Desc": "AOVOPRO ESMINI Electric Scooter 250W 30km/h Smart APP Foldable Electric Scooter 5 Inch Solid Tire Shock Absorbing Scooter",
    "Origin Price": "USD 357.96",
    "Discount Price": "USD 178.98",
    "Discount": "50%",
    "Currency": "USD",
    "Commission Rate": 7,
    "Commission": "USD 12.53",
    "Sales180Day": 8,
    "Positive Feedback": "20.0%",
    "Promotion Url": "https://s.click.aliexpress.com/e/_DB1EGvd",
    "Code Name": "",
    "Code Start Time": "",
    "Code End Time": "",
    "Code Value": "",
    "Code Quantity": "",
    "Code Minimum Spend": ""
  },
  {
    "ProductId": 1005005101562992,
    "Image Url": "https://ae04.alicdn.com/kf/S408fea46367d408c9e75d190bfc8eb38r.jpg",
    "Video Url": "",
    "Product Desc": "500W Electric Scooter 30KM/H Max Speed 50KM Range 36V 15AH 10'' Pneumatic Tire Smart Scooter with APP Adults Commuter E Scooter",
    "Origin Price": "USD 522.00",
    "Discount Price": "USD 469.80",
    "Discount": "10%",
    "Currency": "USD",
    "Commission Rate": 7,
    "Commission": "USD 32.89",
    "Sales180Day": 0,
    "Positive Feedback": "null%",
    "Promotion Url": "https://s.click.aliexpress.com/e/_DnL68iJ",
    "Code Name": "",
    "Code Start Time": "",
    "Code End Time": "",
    "Code Value": "",
    "Code Quantity": "",
    "Code Minimum Spend": ""
  },
  {
    "ProductId": 1005004557004791,
    "Image Url": "https://ae04.alicdn.com/kf/Sa90fc595b4494a54b89f3e397b78fbc77.jpg",
    "Video Url": "http://cloud.video.taobao.com/play/u/2675628091/p/1/e/6/t/1/338881704404.mp4",
    "Product Desc": "30 Ah Battery Electric Scooters Adults E Scooter with Hydraulic Suspension 80km/h Scooter Elecric 11'' Off-road Tires EU USA",
    "Origin Price": "USD 880.00",
    "Discount Price": "USD 660.00",
    "Discount": "25%",
    "Currency": "USD",
    "Commission Rate": 8.5,
    "Commission": "USD 56.10",
    "Sales180Day": 2,
    "Positive Feedback": "100.0%",
    "Promotion Url": "https://s.click.aliexpress.com/e/_DnqNXVt",
    "Code Name": "",
    "Code Start Time": "",
    "Code End Time": "",
    "Code Value": "",
    "Code Quantity": "",
    "Code Minimum Spend": ""
  },
  {
    "ProductId": 1005004830086857,
    "Image Url": "https://ae04.alicdn.com/kf/S5a9fcd0a9d3f4366b05f8b3170a9648cw.jpg",
    "Video Url": "http://cloud.video.taobao.com/play/u/2675628091/p/1/e/6/t/1/1100093057539.mp4",
    "Product Desc": "Electric Scooter Adult Foldable E Scooter 48V18AH 45KM/H Top Speed 60KM Range Powerful Electric Kick Scooter Off-Road Scooter",
    "Origin Price": "USD 722.00",
    "Discount Price": "USD 649.80",
    "Discount": "10%",
    "Currency": "USD",
    "Commission Rate": 7,
    "Commission": "USD 45.49",
    "Sales180Day": 2,
    "Positive Feedback": "100.0%",
    "Promotion Url": "https://s.click.aliexpress.com/e/_Dc7jpMP",
    "Code Name": "",
    "Code Start Time": "",
    "Code End Time": "",
    "Code Value": "",
    "Code Quantity": "",
    "Code Minimum Spend": ""
  },
  {
    "ProductId": 4000714041223,
    "Image Url": "https://ae04.alicdn.com/kf/H2bbd02190f9f420e9085b4940ba7450cv.png",
    "Video Url": "",
    "Product Desc": "2020 Mercane Wide Wheel Pro Smart Electric Scooter 48V 1000W Kickscooter Dual Motor scooter Disc Brake Skate board",
    "Origin Price": "USD 760.00",
    "Discount Price": "USD 760.00",
    "Discount": "0%",
    "Currency": "USD",
    "Commission Rate": 7,
    "Commission": "USD 53.20",
    "Sales180Day": 3,
    "Positive Feedback": "100.0%",
    "Promotion Url": "https://s.click.aliexpress.com/e/_DkbJLkJ",
    "Code Name": "",
    "Code Start Time": "",
    "Code End Time": "",
    "Code Value": "",
    "Code Quantity": "",
    "Code Minimum Spend": ""
  },
  {
    "ProductId": 1005004583712810,
    "Image Url": "https://ae04.alicdn.com/kf/A9bcbac2bf8c0427ba99326b20b959422R.jpg",
    "Video Url": "",
    "Product Desc": "X3 2400W Electric Scooter Large Capacity 48V 21AH Lithium Battery Patinete Elétrico 11-inch Off-road Gliding Wheels Scooters",
    "Origin Price": "USD 1499.00",
    "Discount Price": "USD 1349.10",
    "Discount": "10%",
    "Currency": "USD",
    "Commission Rate": 7,
    "Commission": "USD 94.44",
    "Sales180Day": 1,
    "Positive Feedback": "null%",
    "Promotion Url": "https://s.click.aliexpress.com/e/_Dk5STm3",
    "Code Name": "",
    "Code Start Time": "",
    "Code End Time": "",
    "Code Value": "",
    "Code Quantity": "",
    "Code Minimum Spend": ""
  },
  {
    "ProductId": 1005004958827232,
    "Image Url": "https://ae04.alicdn.com/kf/Sf469c3bf070745fe9e3a54b4e455f3df8.jpg",
    "Video Url": "http://cloud.video.taobao.com/play/u/2675628091/p/1/e/6/t/1/1100100741396.mp4",
    "Product Desc": "2400W High Power Electric Scooter Dual Motor with Seat 48V 18AH E Scooter Dual Light trotinnette electrique 80KM Long Range",
    "Origin Price": "USD 1012.97",
    "Discount Price": "USD 668.56",
    "Discount": "34%",
    "Currency": "USD",
    "Commission Rate": 8,
    "Commission": "USD 53.48",
    "Sales180Day": 0,
    "Positive Feedback": "null%",
    "Promotion Url": "https://s.click.aliexpress.com/e/_Dd5jbST",
    "Code Name": "",
    "Code Start Time": "",
    "Code End Time": "",
    "Code Value": "",
    "Code Quantity": "",
    "Code Minimum Spend": ""
  },
  {
    "ProductId": 1005004045801846,
    "Image Url": "https://ae04.alicdn.com/kf/S07940cfd72a24e4ebb07e0a3d42b35e61.jpg",
    "Video Url": "http://cloud.video.taobao.com/play/u/2675628091/p/1/e/6/t/1/351245284750.mp4",
    "Product Desc": "EU stock Bluetooth  350W Electric Scooter 36V 7.8AH Battery Folding E-scooter for Adult Commute Off Road Safety with Light",
    "Origin Price": "USD 396.00",
    "Discount Price": "USD 376.20",
    "Discount": "5%",
    "Currency": "USD",
    "Commission Rate": 7,
    "Commission": "USD 26.33",
    "Sales180Day": 0,
    "Positive Feedback": "null%",
    "Promotion Url": "https://s.click.aliexpress.com/e/_Dkkl1BH",
    "Code Name": "",
    "Code Start Time": "",
    "Code End Time": "",
    "Code Value": "",
    "Code Quantity": "",
    "Code Minimum Spend": ""
  },
  {
    "ProductId": 1005004654148747,
    "Image Url": "https://ae04.alicdn.com/kf/S9eec8d102270493ebbbfa553d539f3e0F.jpg",
    "Video Url": "http://cloud.video.taobao.com/play/u/2675628091/p/1/e/6/t/1/1100091989552.mp4",
    "Product Desc": "SEALUP 500w 48v13ah Electric Scooters 12\" Tires Folding Fast Offroad Scooter Electric For Adult With Large Led Screen",
    "Origin Price": "USD 1452.36",
    "Discount Price": "USD 871.42",
    "Discount": "40%",
    "Currency": "USD",
    "Commission Rate": 7,
    "Commission": "USD 61.00",
    "Sales180Day": 2,
    "Positive Feedback": "null%",
    "Promotion Url": "https://s.click.aliexpress.com/e/_DciUHR9",
    "Code Name": "",
    "Code Start Time": "",
    "Code End Time": "",
    "Code Value": "",
    "Code Quantity": "",
    "Code Minimum Spend": ""
  },
  {
    "ProductId": 1005004933774983,
    "Image Url": "https://ae04.alicdn.com/kf/S852de603bc87490592046f0819e1db2cE.jpg",
    "Video Url": "http://cloud.video.taobao.com/play/u/2675628091/p/1/e/6/t/1/1100103661602.mp4",
    "Product Desc": "AOVOPRO ESMAX Adult Electric Scooter 10 Inch Inflatable Run-flat Tire 500W Shock Absorption Escooter Foldable Electric Scooter",
    "Origin Price": "USD 1197.96",
    "Discount Price": "USD 598.98",
    "Discount": "50%",
    "Currency": "USD",
    "Commission Rate": 8,
    "Commission": "USD 47.92",
    "Sales180Day": 0,
    "Positive Feedback": "null%",
    "Promotion Url": "https://s.click.aliexpress.com/e/_DFyCgjD",
    "Code Name": "",
    "Code Start Time": "",
    "Code End Time": "",
    "Code Value": "",
    "Code Quantity": "",
    "Code Minimum Spend": ""
  },
  {
    "ProductId": 1005003974285271,
    "Image Url": "https://ae04.alicdn.com/kf/S8a6fa3beadc149d89df1c661fd639a0en.jpg",
    "Video Url": "http://cloud.video.taobao.com/play/u/2675628091/p/1/e/6/t/1/348844032484.mp4",
    "Product Desc": "Max Speed 100 KM/H Adult Electric Scooter 6000W Motor 13 Inch Fat Tire Electric Scooters Dual Motor Electric Scooter Adults",
    "Origin Price": "USD 907.79",
    "Discount Price": "USD 699.00",
    "Discount": "23%",
    "Currency": "USD",
    "Commission Rate": 10.5,
    "Commission": "USD 73.40",
    "Sales180Day": 1,
    "Positive Feedback": "100.0%",
    "Promotion Url": "https://s.click.aliexpress.com/e/_DD80YpV",
    "Code Name": "",
    "Code Start Time": "",
    "Code End Time": "",
    "Code Value": "",
    "Code Quantity": "",
    "Code Minimum Spend": ""
  },
  {
    "ProductId": 1005005044098673,
    "Image Url": "https://ae04.alicdn.com/kf/S5ad186f6df4c4d10ab8690c5dbfd6b04q.jpg",
    "Video Url": "http://cloud.video.taobao.com/play/u/2675628091/p/1/e/6/t/1/1100106958862.mp4",
    "Product Desc": "Free VAT Tax EU Stock OBARTER D5 12inch 48V 35Ah Dual Motor 2*2500W Top Speed 70km/h Powerful Adult 12inch Electric Scooter",
    "Origin Price": "USD 1975.95",
    "Discount Price": "USD 1975.95",
    "Discount": "0%",
    "Currency": "USD",
    "Commission Rate": 7,
    "Commission": "USD 138.32",
    "Sales180Day": 0,
    "Positive Feedback": "null%",
    "Promotion Url": "https://s.click.aliexpress.com/e/_DcZvhrV",
    "Code Name": "",
    "Code Start Time": "",
    "Code End Time": "",
    "Code Value": "",
    "Code Quantity": "",
    "Code Minimum Spend": ""
  },
  {
    "ProductId": 1005004782027103,
    "Image Url": "https://ae04.alicdn.com/kf/S37f0f7747db24823ba450951b052b64fS.jpg",
    "Video Url": "http://cloud.video.taobao.com/play/u/2675628091/p/1/e/6/t/1/1100107155336.mp4",
    "Product Desc": "RU US EU UK  stock high-end adult electric scooter 8.5inch 36V350W folding electric scooter ultra-light smart mobility with APP",
    "Origin Price": "USD 299.00",
    "Discount Price": "USD 269.10",
    "Discount": "10%",
    "Currency": "USD",
    "Commission Rate": 7,
    "Commission": "USD 18.84",
    "Sales180Day": 4,
    "Positive Feedback": "null%",
    "Promotion Url": "https://s.click.aliexpress.com/e/_Dl3guIR",
    "Code Name": "",
    "Code Start Time": "",
    "Code End Time": "",
    "Code Value": "",
    "Code Quantity": "",
    "Code Minimum Spend": ""
  },
  {
    "ProductId": 1005003275414081,
    "Image Url": "https://ae04.alicdn.com/kf/Sd8cc37aee4284844842ccb12963ce0c0c.jpg",
    "Video Url": "http://cloud.video.taobao.com/play/u/2675628091/p/1/e/6/t/1/349634396383.mp4",
    "Product Desc": "Free VAT EU Stock OBARTER X3 11inch 48V 21Ah Dual Motor 2*1200W Top Speed 55km/h Powerful Adults Electric Scooter",
    "Origin Price": "USD 1555.14",
    "Discount Price": "USD 1399.62",
    "Discount": "10%",
    "Currency": "USD",
    "Commission Rate": 7,
    "Commission": "USD 97.97",
    "Sales180Day": 4,
    "Positive Feedback": "100.0%",
    "Promotion Url": "https://s.click.aliexpress.com/e/_DeJFciR",
    "Code Name": "",
    "Code Start Time": "",
    "Code End Time": "",
    "Code Value": "",
    "Code Quantity": "",
    "Code Minimum Spend": ""
  },
  {
    "ProductId": 1005004314618759,
    "Image Url": "https://ae04.alicdn.com/kf/Sa1a5b5aaf9ef4447b03dd84fb8fb2498L.png",
    "Video Url": "",
    "Product Desc": "Electric Scooter Speed Dial Thumb Accelerator For Xiaomi M365 Scooter Accessories Trigger Shifter Dial Scooters Thumb Throttle",
    "Origin Price": "USD 6.61",
    "Discount Price": "USD 4.83",
    "Discount": "27%",
    "Currency": "USD",
    "Commission Rate": 7,
    "Commission": "USD 0.34",
    "Sales180Day": 0,
    "Positive Feedback": "null%",
    "Promotion Url": "https://s.click.aliexpress.com/e/_De9Ga8T",
    "Code Name": "",
    "Code Start Time": "",
    "Code End Time": "",
    "Code Value": "",
    "Code Quantity": "",
    "Code Minimum Spend": ""
  },
  {
    "ProductId": 1005004725460555,
    "Image Url": "https://ae04.alicdn.com/kf/S69c31b670870405db01e560f4df5e5c3K.png",
    "Video Url": "http://cloud.video.taobao.com/play/u/2675628091/p/1/e/6/t/1/338881704404.mp4",
    "Product Desc": "US STOCK Electric Scooter for Adult 5600W Dual Motor 26ah Lithium Battery MAX Range 80KM/H Commuter E-scooter with Remote Key",
    "Origin Price": "USD 1053.00",
    "Discount Price": "USD 716.04",
    "Discount": "32%",
    "Currency": "USD",
    "Commission Rate": 8,
    "Commission": "USD 57.28",
    "Sales180Day": 7,
    "Positive Feedback": "60.0%",
    "Promotion Url": "https://s.click.aliexpress.com/e/_Dn4vCnZ",
    "Code Name": "",
    "Code Start Time": "",
    "Code End Time": "",
    "Code Value": "",
    "Code Quantity": "",
    "Code Minimum Spend": ""
  },
  {
    "ProductId": 1005004652104426,
    "Image Url": "https://ae04.alicdn.com/kf/Sba6904abb5054263b837281e90df54684.jpg",
    "Video Url": "http://cloud.video.taobao.com/play/u/2675628091/p/1/e/6/t/1/1100072645213.mp4",
    "Product Desc": "2000W Dual Motor Fast 45km/h Electric Scooters Adults 10inch Off Road Tire E-scooter 48v 18Ah City SUV Scooter Electric Step",
    "Origin Price": "USD 1105.00",
    "Discount Price": "USD 828.75",
    "Discount": "25%",
    "Currency": "USD",
    "Commission Rate": 8,
    "Commission": "USD 66.30",
    "Sales180Day": 6,
    "Positive Feedback": "100.0%",
    "Promotion Url": "https://s.click.aliexpress.com/e/_DBVLkeB",
    "Code Name": "",
    "Code Start Time": "",
    "Code End Time": "",
    "Code Value": "",
    "Code Quantity": "",
    "Code Minimum Spend": ""
  },
  {
    "ProductId": 1005004579424407,
    "Image Url": "https://ae04.alicdn.com/kf/S6a0be2e5a9af497589810b13310ae45av.jpg",
    "Video Url": "http://cloud.video.taobao.com/play/u/2675628091/p/1/e/6/t/1/332367405668.mp4",
    "Product Desc": "Electric Scooter 25KM/H Adult 8.5 Inches E Scooters 350W 7.5Ah Adult Foldable Electric Skateboard Scooter",
    "Origin Price": "USD 551.78",
    "Discount Price": "USD 281.41",
    "Discount": "49%",
    "Currency": "USD",
    "Commission Rate": 7,
    "Commission": "USD 19.70",
    "Sales180Day": 27,
    "Positive Feedback": "100.0%",
    "Promotion Url": "https://s.click.aliexpress.com/e/_DlpJKiB",
    "Code Name": "",
    "Code Start Time": "",
    "Code End Time": "",
    "Code Value": "",
    "Code Quantity": "",
    "Code Minimum Spend": ""
  },
  {
    "ProductId": 1005005060866162,
    "Image Url": "https://ae04.alicdn.com/kf/S7ed541ef78ce46f6b82221009189cbe6N.png",
    "Video Url": "http://cloud.video.taobao.com/play/u/2675628091/p/1/e/6/t/1/1100109626719.mp4",
    "Product Desc": "Unisex Fat Scooter  500-850W Motor Max Speed 40KM/H Portable Foldable E Scooter For Adult Outdoor Off Road Electric Scooter",
    "Origin Price": "USD 1215.24",
    "Discount Price": "USD 619.77",
    "Discount": "49%",
    "Currency": "USD",
    "Commission Rate": 8,
    "Commission": "USD 49.58",
    "Sales180Day": 1,
    "Positive Feedback": "100.0%",
    "Promotion Url": "https://s.click.aliexpress.com/e/_Ded27Mn",
    "Code Name": "",
    "Code Start Time": "",
    "Code End Time": "",
    "Code Value": "",
    "Code Quantity": "",
    "Code Minimum Spend": ""
  },
  {
    "ProductId": 1005004963708894,
    "Image Url": "https://ae04.alicdn.com/kf/S8c7a063872234903a83bf5bd42a74a62Q.jpg",
    "Video Url": "http://cloud.video.taobao.com/play/u/2675628091/p/1/e/6/t/1/1100101026040.mp4",
    "Product Desc": "Electric Scooter 1000W Electric Scooter Adult 60V 12Ah Lithium Battery For E Scooter 1000W City Coco",
    "Origin Price": "USD 1899.00",
    "Discount Price": "USD 1899.00",
    "Discount": "0%",
    "Currency": "USD",
    "Commission Rate": 7,
    "Commission": "USD 132.93",
    "Sales180Day": 0,
    "Positive Feedback": "null%",
    "Promotion Url": "https://s.click.aliexpress.com/e/_Dduof7z",
    "Code Name": "",
    "Code Start Time": "",
    "Code End Time": "",
    "Code Value": "",
    "Code Quantity": "",
    "Code Minimum Spend": ""
  },
  {
    "ProductId": 1005004193238889,
    "Image Url": "https://ae04.alicdn.com/kf/S1949c6798bce418d9b3a09bf60677e0eP.jpg",
    "Video Url": "http://cloud.video.taobao.com/play/u/2675628091/p/1/e/6/t/1/1100015496225.mp4",
    "Product Desc": "ADULT ELECTR SCOOTER  2400W Fold E Scooter 48V Double Moto Powerful Electric Scooter Off-Road SPEED 60km/h 10 Inch",
    "Origin Price": "USD 1733.54",
    "Discount Price": "USD 866.77",
    "Discount": "50%",
    "Currency": "USD",
    "Commission Rate": 7,
    "Commission": "USD 60.67",
    "Sales180Day": 10,
    "Positive Feedback": "100.0%",
    "Promotion Url": "https://s.click.aliexpress.com/e/_DBEyVCP",
    "Code Name": "",
    "Code Start Time": "",
    "Code End Time": "",
    "Code Value": "",
    "Code Quantity": "",
    "Code Minimum Spend": ""
  },
  {
    "ProductId": 1005004527362063,
    "Image Url": "https://ae04.alicdn.com/kf/A87bace8fe0f1423ab076e24b447b7ff1o.jpg",
    "Video Url": "http://cloud.video.taobao.com/play/u/2675628091/p/1/e/6/t/1/1100066049014.mp4",
    "Product Desc": "Electric Scooter 1200W Super Motor Up To 30 MPH & 40 Miles 10.5\" Off Road Tires Electric Scooter 52V 18AH Disc Brakes for Adults",
    "Origin Price": "USD 1055.00",
    "Discount Price": "USD 949.50",
    "Discount": "10%",
    "Currency": "USD",
    "Commission Rate": 7,
    "Commission": "USD 66.46",
    "Sales180Day": 16,
    "Positive Feedback": "96.7%",
    "Promotion Url": "https://s.click.aliexpress.com/e/_Dlbi6Pt",
    "Code Name": "",
    "Code Start Time": "",
    "Code End Time": "",
    "Code Value": "",
    "Code Quantity": "",
    "Code Minimum Spend": ""
  },
  {
    "ProductId": 1005005134334192,
    "Image Url": "https://ae04.alicdn.com/kf/S4a70d560839140809da38a47abd9b64e7.jpg",
    "Video Url": "http://cloud.video.taobao.com/play/u/2675628091/p/1/e/6/t/1/1100117309329.mp4",
    "Product Desc": "Free VAT Original Kaabo Mantis King GT Mudguard Fender Longer Shorter Extended Fender for Kaabo Mantis King GT Electric Scooter",
    "Origin Price": "USD 38.66",
    "Discount Price": "USD 27.06",
    "Discount": "30%",
    "Currency": "USD",
    "Commission Rate": 7,
    "Commission": "USD 1.89",
    "Sales180Day": 0,
    "Positive Feedback": "null%",
    "Promotion Url": "https://s.click.aliexpress.com/e/_DCdWTcP",
    "Code Name": "",
    "Code Start Time": "",
    "Code End Time": "",
    "Code Value": "",
    "Code Quantity": "",
    "Code Minimum Spend": ""
  },
  {
    "ProductId": 1005002680439043,
    "Image Url": "https://ae04.alicdn.com/kf/S76b50ea3a0ff4b4c87920b62747147b5N.jpg",
    "Video Url": "http://cloud.video.taobao.com/play/u/2675628091/p/1/e/6/t/1/322633649365.mp4",
    "Product Desc": "60V 5600W Dual Motor Electric Scooter 80KM/H Max Speed E Scooter Adults 100KM Long Range trotinette électrique Removeable Seat",
    "Origin Price": "USD 793.99",
    "Discount Price": "USD 611.37",
    "Discount": "23%",
    "Currency": "USD",
    "Commission Rate": 7,
    "Commission": "USD 42.80",
    "Sales180Day": 7,
    "Positive Feedback": "0.0%",
    "Promotion Url": "https://s.click.aliexpress.com/e/_DCoYOif",
    "Code Name": "",
    "Code Start Time": "",
    "Code End Time": "",
    "Code Value": "",
    "Code Quantity": "",
    "Code Minimum Spend": ""
  },
  {
    "ProductId": 1005004645871619,
    "Image Url": "https://ae04.alicdn.com/kf/S260fbcd358684202a3f059b0fbc46313o.jpg",
    "Video Url": "http://cloud.video.taobao.com/play/u/2675628091/p/1/e/6/t/1/1100080503214.mp4",
    "Product Desc": "Hoverboard 8.5 Inch Off-Road Electric Self-Balancing Scooters All-Terrain Hover E-Scooter Board Bluetooth For Adult Kids",
    "Origin Price": "USD 299.00",
    "Discount Price": "USD 209.30",
    "Discount": "30%",
    "Currency": "USD",
    "Commission Rate": 8,
    "Commission": "USD 16.74",
    "Sales180Day": 0,
    "Positive Feedback": "null%",
    "Promotion Url": "https://s.click.aliexpress.com/e/_DmtMiTp",
    "Code Name": "",
    "Code Start Time": "",
    "Code End Time": "",
    "Code Value": "",
    "Code Quantity": "",
    "Code Minimum Spend": ""
  },
  {
    "ProductId": 1005005066160254,
    "Image Url": "https://ae04.alicdn.com/kf/S9b0c70ca85a443298ca01665f431bf6dy.jpg",
    "Video Url": "http://cloud.video.taobao.com/play/u/2675628091/p/1/e/6/t/1/1100110015915.mp4",
    "Product Desc": "Electric Scooter 350W 36V 7.8Ah Max mileage 30 km/h For APP Smart Scooter Shock-absorbing Anti-skid Folding Electric Scooter",
    "Origin Price": "USD 799.00",
    "Discount Price": "USD 399.50",
    "Discount": "50%",
    "Currency": "USD",
    "Commission Rate": 10,
    "Commission": "USD 39.95",
    "Sales180Day": 0,
    "Positive Feedback": "null%",
    "Promotion Url": "https://s.click.aliexpress.com/e/_DEyl10X",
    "Code Name": "",
    "Code Start Time": "",
    "Code End Time": "",
    "Code Value": "",
    "Code Quantity": "",
    "Code Minimum Spend": ""
  },
  {
    "ProductId": 1005004587806261,
    "Image Url": "https://ae04.alicdn.com/kf/S8caa3165c7c846b09b5a1c0b3eab6c70q.jpg",
    "Video Url": "http://cloud.video.taobao.com/play/u/2675628091/p/1/e/6/t/1/1100074176505.mp4",
    "Product Desc": "HEZZO EU US Stock 36V 350W 18.7Mph Electric Scooter 7.8Ah Foldable Xiaomi Pro2 Adult Mobility Escooter Rear Suspension With APP",
    "Origin Price": "USD 399.00",
    "Discount Price": "USD 339.15",
    "Discount": "15%",
    "Currency": "USD",
    "Commission Rate": 7,
    "Commission": "USD 23.74",
    "Sales180Day": 1,
    "Positive Feedback": "80.0%",
    "Promotion Url": "https://s.click.aliexpress.com/e/_DBjPwsj",
    "Code Name": "",
    "Code Start Time": "",
    "Code End Time": "",
    "Code Value": "",
    "Code Quantity": "",
    "Code Minimum Spend": ""
  },
  {
    "ProductId": 1005003275052691,
    "Image Url": "https://ae04.alicdn.com/kf/S8fbc0a45077e4b1bb6d7e0c56b13bd9cA.jpg",
    "Video Url": "http://cloud.video.taobao.com/play/u/2675628091/p/1/e/6/t/1/350151645712.mp4",
    "Product Desc": "Free VAT Tax EU Stock OBARTER X5 13inch 60V 30Ah Dual Motor 5600W Top Speed 85km/h Powerful Adult 13inch Electric Scooter",
    "Origin Price": "USD 2175.87",
    "Discount Price": "USD 2067.07",
    "Discount": "5%",
    "Currency": "USD",
    "Commission Rate": 7,
    "Commission": "USD 144.69",
    "Sales180Day": 11,
    "Positive Feedback": "100.0%",
    "Promotion Url": "https://s.click.aliexpress.com/e/_DCvFGdd",
    "Code Name": "",
    "Code Start Time": "",
    "Code End Time": "",
    "Code Value": "",
    "Code Quantity": "",
    "Code Minimum Spend": ""
  },
  {
    "ProductId": 1005004933015136,
    "Image Url": "https://ae04.alicdn.com/kf/S9768ad20fd19436d8b26a487add04d6dA.png",
    "Video Url": "http://cloud.video.taobao.com/play/u/2675628091/p/1/e/6/t/1/1100098094514.mp4",
    "Product Desc": "AOVOPRO KES1 Safe Kids Electric Scooter with Bluetooth Audio Colorful Lights Kids Scooter Kids Folding Electric Scooter",
    "Origin Price": "USD 397.96",
    "Discount Price": "USD 198.98",
    "Discount": "50%",
    "Currency": "USD",
    "Commission Rate": 8,
    "Commission": "USD 15.92",
    "Sales180Day": 11,
    "Positive Feedback": "100.0%",
    "Promotion Url": "https://s.click.aliexpress.com/e/_DeLOxmj",
    "Code Name": "",
    "Code Start Time": "",
    "Code End Time": "",
    "Code Value": "",
    "Code Quantity": "",
    "Code Minimum Spend": ""
  },
  {
    "ProductId": 1005005082195660,
    "Image Url": "https://ae04.alicdn.com/kf/S5d652a43e397409e8a53d57425898873h.jpg",
    "Video Url": "http://cloud.video.taobao.com/play/u/2675628091/p/1/e/6/t/1/1100059596076.mp4",
    "Product Desc": "RU US EU UK Kr stock high-end adult electric scooter 8.5in 36V350W folding electric scooter ultra-light smart mobility bike M150",
    "Origin Price": "USD 470.00",
    "Discount Price": "USD 235.00",
    "Discount": "50%",
    "Currency": "USD",
    "Commission Rate": 7,
    "Commission": "USD 16.45",
    "Sales180Day": 7,
    "Positive Feedback": "100.0%",
    "Promotion Url": "https://s.click.aliexpress.com/e/_Dm0uqUj",
    "Code Name": "",
    "Code Start Time": "",
    "Code End Time": "",
    "Code Value": "",
    "Code Quantity": "",
    "Code Minimum Spend": ""
  },
  {
    "ProductId": 1005003031656564,
    "Image Url": "https://ae04.alicdn.com/kf/S3bbf63b8a5e94d078b59666b6f30a732K.jpg",
    "Video Url": "",
    "Product Desc": "Free VAT Tax EU Stock ZERO 11X Electric Scooter X11-DDM 72V 32Ah 26Ah Battery Peak 6400W Dual Motor Top Speed 110km/h ZERO 11X",
    "Origin Price": "USD 2744.68",
    "Discount Price": "USD 2744.68",
    "Discount": "0%",
    "Currency": "USD",
    "Commission Rate": 7,
    "Commission": "USD 192.13",
    "Sales180Day": 1,
    "Positive Feedback": "100.0%",
    "Promotion Url": "https://s.click.aliexpress.com/e/_DEIMJCJ",
    "Code Name": "",
    "Code Start Time": "",
    "Code End Time": "",
    "Code Value": "",
    "Code Quantity": "",
    "Code Minimum Spend": ""
  },
  {
    "ProductId": 1005004905889873,
    "Image Url": "https://ae04.alicdn.com/kf/S87cd2664055e4b8caeedd1e1126506b7c.jpg",
    "Video Url": "http://cloud.video.taobao.com/play/u/2675628091/p/1/e/6/t/1/1100096626201.mp4",
    "Product Desc": "Free VAT EU Stock HX X10 48V 18.2Ah Dual Motor 2*1200W Top Speed 40km/h Long Mileage11inch Off-road Tire X10 Electric Scooter",
    "Origin Price": "USD 1791.50",
    "Discount Price": "USD 1379.45",
    "Discount": "23%",
    "Currency": "USD",
    "Commission Rate": 7,
    "Commission": "USD 96.56",
    "Sales180Day": 2,
    "Positive Feedback": "100.0%",
    "Promotion Url": "https://s.click.aliexpress.com/e/_Dm5QjCX",
    "Code Name": "",
    "Code Start Time": "",
    "Code End Time": "",
    "Code Value": "",
    "Code Quantity": "",
    "Code Minimum Spend": ""
  },
  {
    "ProductId": 1005005123633598,
    "Image Url": "https://ae04.alicdn.com/kf/Sc17ca205b9ab46299ffa901f000efc11Y.jpg",
    "Video Url": "",
    "Product Desc": "Powerful Electric scooter Bike 500W 48V Electric Bicycles With Removable Battery 3 Wheel Electric Tricycle For Elderly/Disabled",
    "Origin Price": "USD 3051.85",
    "Discount Price": "USD 305.18",
    "Discount": "90%",
    "Currency": "USD",
    "Commission Rate": 7,
    "Commission": "USD 21.36",
    "Sales180Day": 2,
    "Positive Feedback": "null%",
    "Promotion Url": "https://s.click.aliexpress.com/e/_DEik1xH",
    "Code Name": "",
    "Code Start Time": "",
    "Code End Time": "",
    "Code Value": "",
    "Code Quantity": "",
    "Code Minimum Spend": ""
  },
  {
    "ProductId": 1005004740520757,
    "Image Url": "https://ae04.alicdn.com/kf/S1af8d18758f84593976b870ca1b9ffe8e.jpg",
    "Video Url": "http://cloud.video.taobao.com/play/u/2675628091/p/1/e/6/t/1/1100087573704.mp4",
    "Product Desc": "AOVOPRO M365 Electric Scooter Smart APP 350W 7.8Ah 25km/h E Scooter Foldable Adult Electric Scooter Waterproof Grade IP65",
    "Origin Price": "USD 558.00",
    "Discount Price": "USD 279.00",
    "Discount": "50%",
    "Currency": "USD",
    "Commission Rate": 8,
    "Commission": "USD 22.32",
    "Sales180Day": 1,
    "Positive Feedback": "100.0%",
    "Promotion Url": "https://s.click.aliexpress.com/e/_DezwZsn",
    "Code Name": "",
    "Code Start Time": "",
    "Code End Time": "",
    "Code Value": "",
    "Code Quantity": "",
    "Code Minimum Spend": ""
  },
  {
    "ProductId": 1005004670279342,
    "Image Url": "https://ae04.alicdn.com/kf/Sf25b63726c6e4bbc9ea65e58133a6b49y.jpg",
    "Video Url": "http://cloud.video.taobao.com/play/u/2675628091/p/1/e/6/t/1/1100082893138.mp4",
    "Product Desc": "WHOLESALE NEW SHARING TWO WHEELS PORTABLE SCOOTER HOT SALE KICK FOLDABLE ADULT ELECTRIC SCOOTE SEALUP Q5",
    "Origin Price": "USD 770.64",
    "Discount Price": "USD 462.38",
    "Discount": "40%",
    "Currency": "USD",
    "Commission Rate": 7,
    "Commission": "USD 32.37",
    "Sales180Day": 4,
    "Positive Feedback": "100.0%",
    "Promotion Url": "https://s.click.aliexpress.com/e/_DejbBwb",
    "Code Name": "",
    "Code Start Time": "",
    "Code End Time": "",
    "Code Value": "",
    "Code Quantity": "",
    "Code Minimum Spend": ""
  },
  {
    "ProductId": 1005005010678520,
    "Image Url": "https://ae04.alicdn.com/kf/S1d060fb4034b4f10969b87a9bc50a77cx.png",
    "Video Url": "http://cloud.video.taobao.com/play/u/2675628091/p/1/e/6/t/1/1100105061729.mp4",
    "Product Desc": "48V 2400W Dual Drive Electric Scooter 65km/h Scooter Elecric 11\" Off Road E Scooter Foldable Electric Scooters Adults",
    "Origin Price": "USD 2800.00",
    "Discount Price": "USD 1400.00",
    "Discount": "50%",
    "Currency": "USD",
    "Commission Rate": 10,
    "Commission": "USD 140.00",
    "Sales180Day": 0,
    "Positive Feedback": "null%",
    "Promotion Url": "https://s.click.aliexpress.com/e/_DBu8RW3",
    "Code Name": "",
    "Code Start Time": "",
    "Code End Time": "",
    "Code Value": "",
    "Code Quantity": "",
    "Code Minimum Spend": ""
  },
  {
    "ProductId": 1005004046113017,
    "Image Url": "https://ae04.alicdn.com/kf/S34b5063b93ef4efc8b0c55e104e45104a.jpg",
    "Video Url": "",
    "Product Desc": "10 Inch Electric Scooter 500W Fold E Scooter 48V 12.5A Adult Scooter Black  56-60km Endurance Band Bluetooth Waterproof",
    "Origin Price": "USD 618.00",
    "Discount Price": "USD 587.10",
    "Discount": "5%",
    "Currency": "USD",
    "Commission Rate": 7,
    "Commission": "USD 41.10",
    "Sales180Day": 2,
    "Positive Feedback": "100.0%",
    "Promotion Url": "https://s.click.aliexpress.com/e/_DmDOUFZ",
    "Code Name": "",
    "Code Start Time": "",
    "Code End Time": "",
    "Code Value": "",
    "Code Quantity": "",
    "Code Minimum Spend": ""
  },
  {
    "ProductId": 1005002747803380,
    "Image Url": "https://ae04.alicdn.com/kf/H21ef6a1d68d24c5cbb32c48089614843q.jpg",
    "Video Url": "http://cloud.video.taobao.com/play/u/2675628091/p/1/e/6/t/1/312508761321.mp4",
    "Product Desc": "RU Stock! 3-7 Days Delivery! M365 Electric Kick Scooter 350W 30KM Range 25KM/H 7.8Ah Portable Adult Electric Scooters Dropshippi",
    "Origin Price": "USD 426.99",
    "Discount Price": "USD 426.99",
    "Discount": "0%",
    "Currency": "USD",
    "Commission Rate": 8,
    "Commission": "USD 34.16",
    "Sales180Day": 0,
    "Positive Feedback": "null%",
    "Promotion Url": "https://s.click.aliexpress.com/e/_DELQ2Fp",
    "Code Name": "",
    "Code Start Time": "",
    "Code End Time": "",
    "Code Value": "",
    "Code Quantity": "",
    "Code Minimum Spend": ""
  }
]